petal_leafsdk-0.2.3.dist-info/METADATA
petal_leafsdk-0.2.3.dist-info/WHEEL
petal_leafsdk-0.2.3.dist-info/entry_points.txt
petal_leafsdk/__init__.py
petal_leafsdk/coordinate_utils.py
petal_leafsdk/data_model.py
petal_leafsdk/distributed_memory/types.py
petal_leafsdk/distributed_memory_state/__init__.py
petal_leafsdk/distributed_memory_state/distributed_state_node.py
petal_leafsdk/fc_status_provider.py
petal_leafsdk/fsm.py
petal_leafsdk/heartbeat.py
petal_leafsdk/mavlink_helpers.py
petal_leafsdk/mission.py
petal_leafsdk/mission_queue.py
petal_leafsdk/mission_step.py
petal_leafsdk/plugin.py
petal_leafsdk/redis_helpers.py
petal_leafsdk/setpoint_memory.py
petal_leafsdk-0.2.3.dist-info/RECORD
