Metadata-Version: 2.1
Name: petal-leafsdk
Version: 0.2.3
Summary: SDK for mission planning
Author-Email: Khalil Al Handawi <khalil.alhandawi@droneleaf.io>, Suleyman Yildirim <suleyman.yildirim@droneleaf.io>
License: MIT
Requires-Python: >=3.10
Requires-Dist: petal-app-manager>=0.1.26
Requires-Dist: LeafSDK>=0.3.3
